WinJobster/__init__.py
WinJobster/_meta.py
WinJobster/exceptions.py
WinJobster/job.py
WinJobster/loader.py
libs/WinJobster-x64.dll
libs/WinJobster-x86.dll
libs/get_dlls.py
WinJobster-2.1.0.dist-info/LICENSE.md
WinJobster-2.1.0.dist-info/METADATA
WinJobster-2.1.0.dist-info/WHEEL
WinJobster-2.1.0.dist-info/top_level.txt
WinJobster-2.1.0.dist-info/RECORD
