Metadata-Version: 2.1
Name: WinJobster
Version: 2.1.0
Summary: WinJobster is a library, which can start processes in a Windows job, monitor their state (dead or alive) and kill them all at once, including their children, children of their children... you know where I'm going...
Author: MaxBQb, SemperSolus0x3d
License: GPL-3.0 license
Project-URL: Homepage, https://github.com/SemperSolus0x3d/WinJobster.py
Project-URL: Bug Tracker, https://github.com/SemperSolus0x3d/WinJobster.py/issues
Keywords: windows,windows-jobs,winapi,process,process-groups
Classifier: Programming Language :: Python :: 3
Classifier: Programming Language :: Python :: 3.7
Classifier: Programming Language :: Python :: 3.8
Classifier: Programming Language :: Python :: 3.9
Classifier: Programming Language :: Python :: 3.10
Classifier: Programming Language :: Python :: 3.11
Classifier: Intended Audience :: Developers
Classifier: Natural Language :: English
Classifier: Programming Language :: Python :: Implementation :: CPython
Classifier: Topic :: Software Development :: Libraries :: Python Modules
Classifier: Operating System :: Microsoft :: Windows
Requires-Python: >=3.7
License-File: LICENSE.md
